qesem/__init__.py
qesem/client.py
qesem/helpers.py
qesem/models.py
qesem/py.typed
qesem-0.1.0.dist-info/METADATA
qesem-0.1.0.dist-info/WHEEL
qesem-0.1.0.dist-info/RECORD
