Metadata-Version: 2.3
Name: qesem
Version: 0.1.0
Summary: Qedma QESEM SDK
Author: Qedma Support
Author-email: support@qedma.com
Requires-Python: >=3.10,<4.0
Classifier: Programming Language :: Python :: 3
Classifier: Programming Language :: Python :: 3.10
Classifier: Programming Language :: Python :: 3.11
Classifier: Programming Language :: Python :: 3.12
Classifier: Programming Language :: Python :: 3.13
Requires-Dist: loguru (>=0.7.2,<0.8.0)
Requires-Dist: pydantic (>=2.10.6,<3.0.0)
Requires-Dist: qiskit (>=1.0.2,<2.0.0)
Requires-Dist: qiskit-qasm3-import (>=0.5.1,<0.6.0)
Requires-Dist: requests (>=2.32.3,<3.0.0)
Requires-Dist: typing-extensions (>=4.12.2,<5.0.0)
